Workbook
Name Aporte: APP!$D$16
Name imposto_renda: APP!$D$62
Name inflacao: APP!$D$20
Name lucro_bruto: APP!$D$61
Name patrimonio: APP!$D$19
Name patrimonio_liquido: APP!$D$63
Name perfil: APP!$C$34
Name qtd_anos: APP!$D$17
Name rendimento_carteira: APP!$D$11
Name salario: APP!$D$10
Name sugestao_investimento: APP!$D$12
Name taxa_mensal: APP!$D$18

Sheet APP
A2: CALCULADORA DE INVESTIMENTO
B9: CONFIGURAÇÕES
B10: Salário | D10: 4200
B11: Rendimento carteira | D11: 0.006
B12: Sugestão de Investimento (30%) | D12: =D10*0.3 -> 1260
B15: INVESTIMENTO MENSAL
B16: Investimento por mês | D16: 1260
B17: Números de anos | D17: 10
B18: Taxa de rendimento mensal | D18: 0.01079
A19: 2 | B19: Patrimônio acumulado | D19: =FV(taxa_mensal, qtd_anos*12, Aporte*(-1)) -> 306538.11
B20: Inflação Estimada (ao ano) | D20: 0.045
A21: 5 | B21: Dividendos mensais | D21: =patrimonio*rendimento_carteira -> 1839.2286
A22: 10
A23: 20
A24: 30
B25: CENÁRIOS | D25: Dividendo
B26: Quanto eu teria em 2 anos? | C26: =FV(taxa_mensal, $A19*12, Aporte*(-1)) -> 34306.81 | D26: =C26*rendimento_carteira -> 205.84086
B27: Quanto eu teria em 5 anos? | C27: =FV(taxa_mensal, $A21*12, Aporte*(-1)) -> 105558.91 | D27: =C27*rendimento_carteira -> 633.35347
B28: Quanto eu teria em 10 anos? | C28: =FV(taxa_mensal, $A22*12, Aporte*(-1)) -> 306538.11 | D28: =C28*rendimento_carteira -> 1839.2286
B29: Quanto eu teria em 20 anos? | C29: =FV(taxa_mensal, $A23*12, Aporte*(-1)) -> 1417750 | D29: =C29*rendimento_carteira -> 8506.4999
B30: Quanto eu teria em 30 anos? | C30: =FV(taxa_mensal, $A24*12, Aporte*(-1)) -> 5445933.8 | D30: =C30*rendimento_carteira -> 32675.603
B34: PERFIL | C34: Agressivo
B35: VALOR A SER INVESTIDO POR MÊS | C35: =Aporte -> 1260
B37: TIPO DE FII | C37: Percentual Sugerido | D37: Valores
B38: TIJOLO | C38: =VLOOKUP(perfil&"-"&B38, Planilha2!$A:$D,4, FALSE ) -> 0.1 | D38: =C38*$C$35 -> 126
B39: PAPEL | C39: =VLOOKUP(perfil&"-"&B39, Planilha2!$A:$D,4, FALSE ) -> 0.5 | D39: =C39*$C$35 -> 630
B40: HÍBRIDOS | C40: =VLOOKUP(perfil&"-"&B40, Planilha2!$A:$D,4, FALSE ) -> 0.05 | D40: =C40*$C$35 -> 63
B41: FOFs | C41: =VLOOKUP(perfil&"-"&B41, Planilha2!$A:$D,4, FALSE ) -> 0.05 | D41: =C41*$C$35 -> 63
B42: DESENVOLVIMENTO | C42: =VLOOKUP(perfil&"-"&B42, Planilha2!$A:$D,4, FALSE ) -> 0.2 | D42: =C42*$C$35 -> 252
B43: HOTELARIAS | C43: =VLOOKUP(perfil&"-"&B43, Planilha2!$A:$D,4, FALSE ) -> 0.1 | D43: =C43*$C$35 -> 126
D44: =SUM(D38:D43) -> 1260
B60: Descontos
B61: Lucro Bruto | D61: =patrimonio-Aporte*qtd_anos*12 -> 155338.11
B62: Imposto de Renda sobre o Lucro (20%) | D62: =lucro_bruto*0.2 -> 31067.622
B63: Patrimônio Líquido Nominal | D63: =lucro_bruto-imposto_renda -> 124270.49
B64: Poder de Compra Real | D64: =patrimonio_liquido/((1+inflacao)^qtd_anos) -> 80021.206

Sheet Planilha2
A4: CHAVE | B4: PERFIL | C4: TIPO DE FII | D4: %
A5: =B5&"-"&C5 -> Conservador-TIJOLO | B5: Conservador | C5: TIJOLO | D5: 0.5 | H5: %
A6: =B6&"-"&C6 -> Conservador-PAPEL | B6: Conservador | C6: PAPEL | D6: 0.3 | G6: MODERADO-TIJOLO | H6: =VLOOKUP(G6, A:D, 4,FALSE ) -> 0.35
A7: =B7&"-"&C7 -> Conservador-HÍBRIDOS | B7: Conservador | C7: HÍBRIDOS | D7: 0.1
A8: =B8&"-"&C8 -> Conservador-FOFs | B8: Conservador | C8: FOFs | D8: 0.1
A9: =B9&"-"&C9 -> Conservador-DESENVOLVIMENTO | B9: Conservador | C9: DESENVOLVIMENTO | D9: 0
A10: =B10&"-"&C10 -> Conservador-HOTELARIAS | B10: Conservador | C10: HOTELARIAS | D10: 0
A11: =B11&"-"&C11 -> Moderado-TIJOLO | B11: Moderado | C11: TIJOLO | D11: 0.35
A12: =B12&"-"&C12 -> Moderado-PAPEL | B12: Moderado | C12: PAPEL | D12: 0.32
A13: =B13&"-"&C13 -> Moderado-HÍBRIDOS | B13: Moderado | C13: HÍBRIDOS | D13: 0.08
A14: =B14&"-"&C14 -> Moderado-FOFs | B14: Moderado | C14: FOFs | D14: 0.05
A15: =B15&"-"&C15 -> Moderado-DESENVOLVIMENTO | B15: Moderado | C15: DESENVOLVIMENTO | D15: 0.1
A16: =B16&"-"&C16 -> Moderado-HOTELARIAS | B16: Moderado | C16: HOTELARIAS | D16: 0.1
A17: =B17&"-"&C17 -> Agressivo-TIJOLO | B17: Agressivo | C17: TIJOLO | D17: 0.1
A18: =B18&"-"&C18 -> Agressivo-PAPEL | B18: Agressivo | C18: PAPEL | D18: 0.5
... A22: =B22&"-"&C22 -> Agressivo-HOTELARIAS | B22: Agressivo | C22: HOTELARIAS | D22: 0.1
